biolearns/__init__.py
biolearns/coexpression/__init__.py
biolearns/coexpression/_lmQCM.py
biolearns/coexpression/lmQCM.py
biolearns/dataset/TCGA.py
biolearns/dataset/_TCGA.py
biolearns/dataset/__init__.py
biolearns/decomposition/__init__.py
biolearns/decomposition/_nmf.py
biolearns/metrics/__init__.py
biolearns/metrics/discriminant.py
biolearns/preprocessing/__init__.py
biolearns/preprocessing/_filter.py
biolearns/preprocessing/filter.py
biolearns/survival/__init__.py
biolearns/survival/_coxmodel.py
biolearns/survival/_logranktest.py
biolearns/survival/_newton_rhapson_for_efron_model.py
biolearns-0.0.61.dist-info/LICENSE
biolearns-0.0.61.dist-info/METADATA
biolearns-0.0.61.dist-info/WHEEL
biolearns-0.0.61.dist-info/top_level.txt
biolearns-0.0.61.dist-info/RECORD
