Metadata-Version: 2.1
Name: biolearns
Version: 0.0.61
Summary: BioLearns: Computational Biology and Bioinformatics Toolbox in Python
Home-page: http://biolearns.com
Author: Zhi Huang
Author-email: hz9423@gmail.com
License: UNKNOWN
Platform: UNKNOWN
Classifier: Programming Language :: Python :: 3
Classifier: License :: OSI Approved :: MIT License
Classifier: Operating System :: OS Independent
Requires-Python: >=3.6
